[
  {
    "id": 1,
    "listTitle": "고양이",
    "age": 48,
    "gender": "male",
    "location": "맥시코"
  },
  {
    "id": 2,
    "listTitle": "고냥이",
    "age": 134,
    "gender": "female",
    "location": "양평"
  },
  {
    "id": 3,
    "listTitle": "고용이",
    "age": 7,
    "gender": "male",
    "location": "천안"
  },
  {
    "id": 4,
    "listTitle": "모욜이",
    "age": 19,
    "gender": "female",
    "location": "우크라이나"
  },
  {
    "id": 5,
    "listTitle": "고뮬이",
    "age": 9,
    "gender": "male",
    "location": "전주"
  },
  {
    "id": 6,
    "listTitle": "기양이",
    "age": 2,
    "gender": "male",
    "location": "충청"
  },
  {
    "id": 7,
    "listTitle": "곰냥이",
    "age": 44,
    "gender": "female",
    "location": "LA"
  },
  {
    "id": 8,
    "listTitle": "개냥이",
    "age": 134,
    "gender": "female",
    "location": "아프리카"
  }
]
